xiaobai_config/__init__.py
xiaobai_config/converter.py
xiaobai_config/core.py
xiaobai_config/exceptions.py
xiaobai_config-1.1.dist-info/LICENSE
xiaobai_config-1.1.dist-info/METADATA
xiaobai_config-1.1.dist-info/WHEEL
xiaobai_config-1.1.dist-info/top_level.txt
xiaobai_config-1.1.dist-info/RECORD
