Metadata-Version: 2.1
Name: xiaobai_config
Version: 1.1
Summary: A small tool to parse and store project config
Author: xiaobai
Author-email: xiaobaizrx@gmail.com
Classifier: Programming Language :: Python :: 3
Classifier: Operating System :: OS Independent
License-File: LICENSE
